[
  {
    "TIME": "5:20PM",
    "NAME": "THE vertem.co.uk HANDICAP STAKES (CLASS 6)",
    "DISTANCE": "1m 4f 98y",
    "WINNER": "The Resdev Way",
    "URL": "result/#!/2016/12382/22355/0/",
    "details": {
      "Runners:": "13 RUNNERS",
      "Prize Money:": "£3,500.00",
      "Race Distance:": "1m 4f 98y",
      "Race Going:": "Standard",
      "Horse Age:": "3YO+",
      "Rating:": "46-60",
      "Min Weight:": "8st 12lbs"
    },
    "horses": [
      {
        "POS": "DNF",
        "HORSE/JOCKEY": "Baileys Galaxy (FR)\nJoe Fanning\nHandicap Ran Off:55\nBHA Performance Figure: 0",
        "TRAINER/OWNER": "Mark Johnston\nG. R. Bailey Ltd (Baileys Horse Feeds)",
        "SP": "20/1"
      },
      {
        "POS": "1st",
        "HORSE/JOCKEY": "The Resdev Way (GB)\nBarry McHugh\nHandicap Ran Off:56\nBHA Performance Figure: 67\nCurrent handicap mark: T:47",
        "TRAINER/OWNER": "Richard Whitaker\nResdev",
        "DISTANCES/TIMES": "2m 40.55s",
        "SP": "6/4"
      },
      {
        "POS": "2nd",
        "HORSE/JOCKEY": "Taopix (GB)\nJoey Haynes\nHandicap Ran Off:54\nBHA Performance Figure: 58",
        "TRAINER/OWNER": "Karen McLintock\nMr Roger Stockdale",
        "DISTANCES/TIMES": "2 lengths\n2m 40.91s",
        "SP": "4/1"
      },
      {
        "POS": "3rd",
        "HORSE/JOCKEY": "Kerry Icon (GB)\nAndrew Mullen\nHandicap Ran Off:46\nBHA Performance Figure: 38",
        "TRAINER/OWNER": "Iain Jardine\nMr C J Pickering & Mr Michael Wares",
        "DISTANCES/TIMES": "8 lengths\n2m 42.29s",
        "SP": "20/1"
      },
      {
        "POS": "4th",
        "HORSE/JOCKEY": "Gabrial's Hope (FR)\nDale Swift\nHandicap Ran Off:55\nBHA Performance Figure: 46",
        "TRAINER/OWNER": "Tracy Waggott\nMr David Tate",
        "DISTANCES/TIMES": "1 length\n2m 42.45s",
        "SP": "50/1"
      },
      {
        "POS": "5th",
        "HORSE/JOCKEY": "Zingiber (GB)\nCam Hardie\nHandicap Ran Off:46\nBHA Performance Figure: 36",
        "TRAINER/OWNER": "Wilf Storey\nThistle & Rose Racing 1",
        "DISTANCES/TIMES": "½ length\n2m 42.53s",
        "SP": "100/1"
      },
      {
        "POS": "6th",
        "HORSE/JOCKEY": "Byronegetonefree (GB)\nJason Hart\nHandicap Ran Off:55\nBHA Performance Figure: 43",
        "TRAINER/OWNER": "Stuart Coltherd\nColtherd Conchar",
        "DISTANCES/TIMES": "1½ length\n2m 42.79s",
        "SP": "6/1"
      },
      {
        "POS": "7th",
        "HORSE/JOCKEY": "Sunshineandbubbles (GB)\nLuke Morris\nHandicap Ran Off:57\nBHA Performance Figure: 42",
        "TRAINER/OWNER": "Daniel Loughnane\nAmazing Racing",
        "DISTANCES/TIMES": "2¼ lengths\n2m 43.15s",
        "SP": "11/1"
      },
      {
        "POS": "8th",
        "HORSE/JOCKEY": "Merchant of Dubai (GB)\nLewis Edmunds\nHandicap Ran Off:56\nBHA Performance Figure: 41",
        "TRAINER/OWNER": "Jim Goldie\nHighland Racing 2",
        "DISTANCES/TIMES": "nose\n2m 43.15s",
        "SP": "22/1"
      },
      {
        "POS": "9th",
        "HORSE/JOCKEY": "Magical Lasso (IRE)\nConnor Beasley\nHandicap Ran Off:49\nBHA Performance Figure: 30",
        "TRAINER/OWNER": "Keith Dalgleish\nMiddleham Park Racing CXX",
        "DISTANCES/TIMES": "2¾ lengths\n2m 43.61s",
        "SP": "11/1"
      },
      {
        "POS": "10th",
        "HORSE/JOCKEY": "Breton Blues (GB)\nGraham Lee\nHandicap Ran Off:50\nBHA Performance Figure: 22",
        "TRAINER/OWNER": "Fred Watson\nMr F. Watson",
        "DISTANCES/TIMES": "6 lengths\n2m 44.63s",
        "SP": "16/1"
      },
      {
        "POS": "11th",
        "HORSE/JOCKEY": "Ronald Gee (IRE)\nAdam McNamara\nHandicap Ran Off:59\nBHA Performance Figure: 22",
        "TRAINER/OWNER": "Jim Goldie\nWhitestonecliffe Racing Partnership",
        "DISTANCES/TIMES": "6 lengths\n2m 45.55s",
        "SP": "50/1"
      },
      {
        "POS": "12th",
        "HORSE/JOCKEY": "Applejack Lad (GB)\nPaul Mulrennan\nHandicap Ran Off:54\nBHA Performance Figure: 0",
        "TRAINER/OWNER": "Michael Smith\nOwnaracehorse Ltd (ownaracehorse.co.uk)",
        "DISTANCES/TIMES": "99+\n3m 21.47s",
        "SP": "50/1"
      },
      {
        "POS": "NR",
        "HORSE/JOCKEY": "Loose Ends (GB)\nNon Runner",
        "TRAINER/OWNER": "David Simcock\nMr C. G. P. Wyatt",
        "SP": "--"
      }
    ]
  },
  {
    "TIME": "5:50PM",
    "NAME": "THE PROTECTING YOUR WEALTH HANDICAP STAKES (CLASS 6)",
    "DISTANCE": "1m 2f 42y",
    "WINNER": "Bollihope",
    "URL": "result/#!/2016/12382/22354/0/",
    "details": {
      "Runners:": "13 RUNNERS",
      "Prize Money:": "£3,500.00",
      "Race Distance:": "1m 2f 42y",
      "Race Going:": "Standard",
      "Horse Age:": "3YO+",
      "Rating:": "51-65",
      "Min Weight:": "8st 10lbs"
    },
    "horses": [
      {
        "POS": "1st",
        "HORSE/JOCKEY": "Bollihope (GB)\nJason Hart\nHandicap Ran Off:58\nBHA Performance Figure: 65",
        "TRAINER/OWNER": "Richard Guest\nMrs Alison Guest",
        "DISTANCES/TIMES": "2m 10.16s",
        "SP": "20/1"
      },
      {
        "POS": "2nd",
        "HORSE/JOCKEY": "Testa Rossa (IRE)\nLewis Edmunds\nHandicap Ran Off:60\nBHA Performance Figure: 64",
        "TRAINER/OWNER": "Jim Goldie\nMr & Mrs Gordon Grant",
        "DISTANCES/TIMES": "*1¼ length\n2m 10.35s",
        "SP": "12/1"
      },
      {
        "POS": "3rd",
        "HORSE/JOCKEY": "Roman de Brut (IRE)\nLuke Morris\nHandicap Ran Off:64\nBHA Performance Figure: 62",
        "TRAINER/OWNER": "Daniel Loughnane\nMr Phil Slater",
        "DISTANCES/TIMES": "3¼ lengths\n2m 10.87s",
        "SP": "9/2"
      },
      {
        "POS": "4th",
        "HORSE/JOCKEY": "Cliff Edge (IRE)\nJack Mitchell\nHandicap Ran Off:63\nBHA Performance Figure: 61",
        "TRAINER/OWNER": "Roger Varian\nThurloe Thoroughbreds XXXVI",
        "DISTANCES/TIMES": "neck\n2m 10.92s",
        "SP": "11/4"
      },
      {
        "POS": "5th",
        "HORSE/JOCKEY": "Ajman Prince (IRE)\nRowan Scott\nHandicap Ran Off:65\nBHA Performance Figure: 61",
        "TRAINER/OWNER": "Alistair Whillans\nMr J. D. Wright",
        "DISTANCES/TIMES": "1¼ length\n2m 11.12s",
        "SP": "16/1"
      },
      {
        "POS": "6th",
        "HORSE/JOCKEY": "She's Electric (IRE)\nConnor Beasley\nHandicap Ran Off:62\nBHA Performance Figure: 57",
        "TRAINER/OWNER": "Keith Dalgleish\nWeldspec Glasgow Limited",
        "DISTANCES/TIMES": "¾ length\n2m 11.23s",
        "SP": "33/1"
      },
      {
        "POS": "7th",
        "HORSE/JOCKEY": "Thermal Column (IRE)\nAndrew Mullen\nHandicap Ran Off:64\nBHA Performance Figure: 54",
        "TRAINER/OWNER": "Michael Appleby\nMr Martyn Elvin",
        "DISTANCES/TIMES": "3 lengths\n2m 11.73s",
        "SP": "12/1"
      },
      {
        "POS": "8th",
        "HORSE/JOCKEY": "Best Tamayuz (GB)\nBen Curtis\nHandicap Ran Off:65\nBHA Performance Figure: 53",
        "TRAINER/OWNER": "Scott Dixon\nP J Dixon & Partners",
        "DISTANCES/TIMES": "1 length\n2m 11.88s",
        "SP": "12/1"
      },
      {
        "POS": "9th",
        "HORSE/JOCKEY": "Arantes (GB)\nP. J. McDonald\nHandicap Ran Off:56\nBHA Performance Figure: 42",
        "TRAINER/OWNER": "R. Mike Smith\nSmith Millar Russell",
        "DISTANCES/TIMES": "1¼ length\n2m 12.11s",
        "SP": "33/1"
      },
      {
        "POS": "10th",
        "HORSE/JOCKEY": "Intrigue (GB)\nJim Crowley\nHandicap Ran Off:65\nBHA Performance Figure: 46",
        "TRAINER/OWNER": "Daniel Kubler\nMr & Mrs G. Middlebrook",
        "DISTANCES/TIMES": "3 lengths\n2m 12.62s",
        "SP": "7/2"
      },
      {
        "POS": "11th",
        "HORSE/JOCKEY": "Thornaby Nash (GB)\nTom Eaves\nHandicap Ran Off:65\nBHA Performance Figure: 25",
        "TRAINER/OWNER": "Colin Teague\nMr Dave Scott",
        "DISTANCES/TIMES": "12 lengths\n2m 14.62s",
        "SP": "33/1"
      },
      {
        "POS": "12th",
        "HORSE/JOCKEY": "Symbolic Star (IRE)\nGraham Lee\nHandicap Ran Off:65\nBHA Performance Figure: 25",
        "TRAINER/OWNER": "Barry Murtagh\nMurtagh, O'Rourke & Trinders",
        "DISTANCES/TIMES": "neck\n2m 14.66s",
        "SP": "20/1"
      },
      {
        "POS": "13th",
        "HORSE/JOCKEY": "Nelson's Bay (GB)\nCam Hardie\nHandicap Ran Off:54\nBHA Performance Figure: 7",
        "TRAINER/OWNER": "Wilf Storey\nThe Durham Company & W Storey",
        "DISTANCES/TIMES": "4 lengths\n2m 15.35s",
        "SP": "20/1"
      },
      {
        "POS": "NR",
        "HORSE/JOCKEY": "The Name's Paver (GB)\nNon Runner",
        "TRAINER/OWNER": "Noel Wilson\nMrs Michael John Paver",
        "SP": "--"
      }
    ]
  },
  {
    "TIME": "6:20PM",
    "NAME": "THE @vertemam FOLLOW US ON TWITTER FILLIES' HANDICAP STAKES (CLASS 5)",
    "DISTANCE": "1m 2f 42y",
    "WINNER": "Island Flame (IRE)",
    "URL": "result/#!/2016/12382/22359/0/",
    "details": {
      "Runners:": "7 RUNNERS",
      "Prize Money:": "£5,000.00",
      "Race Distance:": "1m 2f 42y",
      "Race Going:": "Standard",
      "Horse Age:": "3YO+",
      "Horse Sex:": "FILLIES & MARES",
      "Rating:": "56-75",
      "Min Weight:": "8st 7lbs",
      "Weights Raised:": "1lbs"
    },
    "horses": [
      {
        "POS": "1st",
        "HORSE/JOCKEY": "Island Flame (IRE)\nPaddy Mathers\nHandicap Ran Off:70\nBHA Performance Figure: 76",
        "TRAINER/OWNER": "Richard Fahey\nNorthumbria Leisure Ltd",
        "DISTANCES/TIMES": "2m 10.67s",
        "SP": "8/1"
      },
      {
        "POS": "2nd",
        "HORSE/JOCKEY": "All The Rage (GB)\nLuke Morris\nHandicap Ran Off:70\nBHA Performance Figure: 75",
        "TRAINER/OWNER": "Sir Mark Prescott Bt\nDenford Stud",
        "DISTANCES/TIMES": "head\n2m 10.69s",
        "SP": "2/1"
      },
      {
        "POS": "3rd",
        "HORSE/JOCKEY": "High On Light (GB)\nRachel Richardson\nHandicap Ran Off:67\nBHA Performance Figure: 65",
        "TRAINER/OWNER": "Tim Easterby\nHabton Farms",
        "DISTANCES/TIMES": "4 lengths\n2m 11.35s",
        "SP": "5/1"
      },
      {
        "POS": "4th",
        "HORSE/JOCKEY": "Heart Locket (GB)\nNathan Evans\nHandicap Ran Off:71\nBHA Performance Figure: 65",
        "TRAINER/OWNER": "Michael Easterby\nA Chandler & L Westwood 1",
        "DISTANCES/TIMES": "2½ lengths\n2m 11.78s",
        "SP": "11/1"
      },
      {
        "POS": "5th",
        "HORSE/JOCKEY": "Sepal (USA)\nJim Crowley\nHandicap Ran Off:74\nBHA Performance Figure: 63",
        "TRAINER/OWNER": "Charles Hills\nMr K. Abdullah",
        "DISTANCES/TIMES": "3 lengths\n2m 12.29s",
        "SP": "4/1"
      },
      {
        "POS": "6th",
        "HORSE/JOCKEY": "La Havrese (FR)\nPaddy Aspell\nHandicap Ran Off:65\nBHA Performance Figure: 53",
        "TRAINER/OWNER": "Lynn Siddall\nMr Jimmy Kay",
        "DISTANCES/TIMES": "¾ length\n2m 12.41s",
        "SP": "18/1"
      },
      {
        "POS": "7th",
        "HORSE/JOCKEY": "Malhama (GB)\nPaul Hanagan\nHandicap Ran Off:71\nBHA Performance Figure: 36",
        "TRAINER/OWNER": "Roger Varian\nMr Hamdan Al Maktoum",
        "DISTANCES/TIMES": "14 lengths\n2m 14.73s",
        "SP": "5/1"
      },
      {
        "POS": "NR",
        "HORSE/JOCKEY": "Unsuspected Girl (IRE)\nNon Runner",
        "TRAINER/OWNER": "David Simcock\nThe Thoroughbred Club",
        "SP": "--"
      },
      {
        "POS": "NR",
        "HORSE/JOCKEY": "Beadlam (IRE)\nNon Runner",
        "TRAINER/OWNER": "Roger Fell\nMr R. G. Fell",
        "SP": "--"
      },
      {
        "POS": "NR",
        "HORSE/JOCKEY": "Regal Ways (IRE)\nNon Runner",
        "TRAINER/OWNER": "Brian Ellison\nCPM Group Ltd & Brian Ellison",
        "SP": "--"
      }
    ]
  },
  {
    "TIME": "6:50PM",
    "NAME": "THE PERFECT PARTNERSHIPS NURSERY HANDICAP STAKES (CLASS 6)",
    "DISTANCE": "1m 5y",
    "WINNER": "Lucy's Law (IRE)",
    "URL": "result/#!/2016/12382/22357/0/",
    "details": {
      "Runners:": "10 RUNNERS",
      "Prize Money:": "£3,500.00",
      "Race Distance:": "1m 5y",
      "Race Going:": "Standard",
      "Horse Age:": "2YO",
      "Rating:": "0-65",
      "Min Weight:": "8st 1lbs",
      "Weights Raised:": "1lbs"
    },
    "horses": [
      {
        "POS": "1st",
        "HORSE/JOCKEY": "Lucy's Law (IRE)\nAndrew Elliott\nHandicap Ran Off:59\nBHA Performance Figure: 68",
        "TRAINER/OWNER": "Tom Tate\nMs Fionnuala Cassidy",
        "DISTANCES/TIMES": "1m 40.93s",
        "SP": "14/1"
      },
      {
        "POS": "2nd",
        "HORSE/JOCKEY": "Snookered (IRE)\nTony Hamilton\nHandicap Ran Off:52\nBHA Performance Figure: 58",
        "TRAINER/OWNER": "Richard Fahey\nMr Kristian Strangeway",
        "DISTANCES/TIMES": "1½ length\n1m 41.16s",
        "SP": "6/1"
      },
      {
        "POS": "3rd",
        "HORSE/JOCKEY": "Vinnievanbaileys (GB)\nDavid Allan\nHandicap Ran Off:60\nBHA Performance Figure: 62",
        "TRAINER/OWNER": "Chris Dwyer\nG. R. Bailey Ltd (Baileys Horse Feeds)",
        "DISTANCES/TIMES": "1¾ length\n1m 41.44s",
        "SP": "8/1"
      },
      {
        "POS": "4th",
        "HORSE/JOCKEY": "Zamadance (GB)\nJim Crowley\nHandicap Ran Off:62\nBHA Performance Figure: 63",
        "TRAINER/OWNER": "Sylvester Kirk\nMr J. C. Smith",
        "DISTANCES/TIMES": "¾ length\n1m 41.56s",
        "SP": "15/8"
      },
      {
        "POS": "5th",
        "HORSE/JOCKEY": "Cliff Bay (IRE)\nConnor Beasley\nHandicap Ran Off:56\nBHA Performance Figure: 56",
        "TRAINER/OWNER": "Keith Dalgleish\nMr David McKenzie",
        "DISTANCES/TIMES": "neck\n1m 41.61s",
        "SP": "10/1"
      },
      {
        "POS": "6th",
        "HORSE/JOCKEY": "Dominating (GER)\nJoe Fanning\nHandicap Ran Off:62\nBHA Performance Figure: 59",
        "TRAINER/OWNER": "Mark Johnston\nMr A. D. Spence",
        "DISTANCES/TIMES": "1¾ length\n1m 41.9s",
        "SP": "8/1"
      },
      {
        "POS": "7th",
        "HORSE/JOCKEY": "Spanish Beauty (GB)\nJacob Butterfield\nHandicap Ran Off:54\nBHA Performance Figure: 49",
        "TRAINER/OWNER": "Ollie Pears\nOwnaracehorse Ltd (ownaracehorse.co.uk)",
        "DISTANCES/TIMES": "1 length\n1m 42.08s",
        "SP": "50/1"
      },
      {
        "POS": "8th",
        "HORSE/JOCKEY": "On Show (IRE)\nLuke Morris\nHandicap Ran Off:45\nBHA Performance Figure: 39",
        "TRAINER/OWNER": "David Brown\nMr J. C. Fretwell",
        "DISTANCES/TIMES": "½ length\n1m 42.18s",
        "SP": "16/1"
      },
      {
        "POS": "9th",
        "HORSE/JOCKEY": "Belle's Angel (IRE)\nPaul Hanagan\nHandicap Ran Off:49\nBHA Performance Figure: 41",
        "TRAINER/OWNER": "Ann Duffield\nMiddleham Park Racing LXXXV & Partner",
        "DISTANCES/TIMES": "1¼ length\n1m 42.37s",
        "SP": "16/1"
      },
      {
        "POS": "10th",
        "HORSE/JOCKEY": "Bridal March (GB)\nSilvestre De Sousa\nHandicap Ran Off:64\nBHA Performance Figure: 50",
        "TRAINER/OWNER": "Mark Johnston\nMr C. C. Buckley",
        "DISTANCES/TIMES": "3¼ lengths\n1m 42.9s",
        "SP": "13/2"
      }
    ]
  },
  {
    "TIME": "7:20PM",
    "NAME": "THE VERTEM MANAGEMENT/BRITISH STALLIONS STUDS EBF MAIDEN STAKES (CLASS 5)",
    "DISTANCE": "1m 5y",
    "WINNER": "Mandarin (GER)",
    "URL": "result/#!/2016/12382/33233/0/",
    "details": {
      "Runners:": "11 RUNNERS",
      "Prize Money:": "£5,500.00",
      "Race Distance:": "1m 5y",
      "Race Going:": "Standard",
      "Horse Age:": "2YO",
      "Horse Type:": "MAIDEN"
    },
    "horses": [
      {
        "POS": "1st",
        "HORSE/JOCKEY": "Mandarin (GER)\nSilvestre De Sousa",
        "TRAINER/OWNER": "Marco Botti\nSheikh Mohammed bin Khalifa Al Maktoum",
        "DISTANCES/TIMES": "1m 39.12s",
        "SP": "10/11"
      },
      {
        "POS": "2nd",
        "HORSE/JOCKEY": "Cool Team (IRE)\nJim Crowley",
        "TRAINER/OWNER": "Hugo Palmer\nMr Lit Lung Lee",
        "DISTANCES/TIMES": "3¾ lengths\n1m 39.75s",
        "SP": "10/1"
      },
      {
        "POS": "3rd",
        "HORSE/JOCKEY": "Glendun (USA)\nPaul Mulrennan",
        "TRAINER/OWNER": "Brian Meehan\nEmma Capon & Mrs Simon Marsh",
        "DISTANCES/TIMES": "2¼ lengths\n1m 40.12s",
        "SP": "13/2"
      },
      {
        "POS": "4th",
        "HORSE/JOCKEY": "Pathway To Freedom (GB)\nJames Doyle",
        "TRAINER/OWNER": "Charlie Appleby\nGodolphin",
        "DISTANCES/TIMES": "1¾ length\n1m 40.42s",
        "SP": "5/2"
      },
      {
        "POS": "5th",
        "HORSE/JOCKEY": "Rosarno (IRE)\nPaul Hanagan",
        "TRAINER/OWNER": "Charles Hills\nMr Abdulla Al Khalifa",
        "DISTANCES/TIMES": "2 lengths\n1m 40.76s",
        "SP": "20/1"
      },
      {
        "POS": "6th",
        "HORSE/JOCKEY": "La Vie En Rose (GB)\nJoe Fanning",
        "TRAINER/OWNER": "Mark Johnston\nMiss K. Rausing",
        "DISTANCES/TIMES": "6 lengths\n1m 41.82s",
        "SP": "25/1"
      },
      {
        "POS": "7th",
        "HORSE/JOCKEY": "Starshell (IRE)\nLuke Morris",
        "TRAINER/OWNER": "Sir Mark Prescott Bt\nJohn Brown & Megan Dennis",
        "DISTANCES/TIMES": "¾ length\n1m 41.94s",
        "SP": "25/1"
      },
      {
        "POS": "8th",
        "HORSE/JOCKEY": "Siyahamba (IRE)\nConnor Beasley",
        "TRAINER/OWNER": "Bryan Smart\nMr B. Smart",
        "DISTANCES/TIMES": "½ length\n1m 42.01s",
        "SP": "125/1"
      },
      {
        "POS": "9th",
        "HORSE/JOCKEY": "Little Kingdom (IRE)\nPhil Dennis",
        "TRAINER/OWNER": "Tracy Waggott\nMr Steve Sawley",
        "DISTANCES/TIMES": "1½ length\n1m 42.26s",
        "SP": "200/1"
      },
      {
        "POS": "10th",
        "HORSE/JOCKEY": "New Society (IRE)\nP. J. McDonald",
        "TRAINER/OWNER": "James Bethell\nMr John Dance",
        "DISTANCES/TIMES": "10 lengths\n1m 44s",
        "SP": "33/1"
      },
      {
        "POS": "11th",
        "HORSE/JOCKEY": "Thenewsfromspain (IRE)\nAndrew Mullen",
        "TRAINER/OWNER": "Ollie Pears\nMr Charles Wentworth",
        "DISTANCES/TIMES": "4 lengths\n1m 44.67s",
        "SP": "200/1"
      }
    ]
  },
  {
    "TIME": "7:50PM",
    "NAME": "THE FRESH APPROACH/ebfstallions.com MAIDEN FILLIES' STAKES CLASS 5) (PLUS 10 RACE)",
    "DISTANCE": "6f",
    "WINNER": "Castleacre",
    "URL": "result/#!/2016/12382/33231/0/",
    "details": {
      "Runners:": "14 RUNNERS",
      "Prize Money:": "£5,500.00",
      "Race Distance:": "6f",
      "Race Going:": "Standard",
      "Horse Age:": "2YO",
      "Horse Type:": "MAIDEN",
      "Horse Sex:": "FILLIES & MARES"
    },
    "horses": [
      {
        "POS": "1st",
        "HORSE/JOCKEY": "Castleacre (GB)\nJim Crowley",
        "TRAINER/OWNER": "Hugo Palmer\nMr Saeed Manana",
        "DISTANCES/TIMES": "1m 12.09s",
        "SP": "6/4"
      },
      {
        "POS": "2nd",
        "HORSE/JOCKEY": "Dandy Bird (IRE)\nTom Eaves",
        "TRAINER/OWNER": "James Given\nBolton Grange",
        "DISTANCES/TIMES": "4 ½ lengths\n1m 12.81s",
        "SP": "40/1"
      },
      {
        "POS": "3rd",
        "HORSE/JOCKEY": "Ocean Princess (IRE)\nPaul Mulrennan",
        "TRAINER/OWNER": "Michael Dods\nGeoff & Sandra Turnbull",
        "DISTANCES/TIMES": "*1¾ length\n1m 13.08s",
        "SP": "16/1"
      },
      {
        "POS": "4th",
        "HORSE/JOCKEY": "Bearag (GB)\nPhillip Makin",
        "TRAINER/OWNER": "David O'Meara\nMr Hamad Rashed Bin Ghedayer",
        "DISTANCES/TIMES": "head\n1m 13.1s",
        "SP": "33/1"
      },
      {
        "POS": "5th",
        "HORSE/JOCKEY": "Al Haayelah (GB)\nJack Mitchell",
        "TRAINER/OWNER": "Roger Varian\nKhalid Bin Ali Al Khalifa",
        "DISTANCES/TIMES": "½ length\n1m 13.18s",
        "SP": "14/1"
      },
      {
        "POS": "6th",
        "HORSE/JOCKEY": "Dazacam (GB)\nDougie Costello",
        "TRAINER/OWNER": "Michael Herrington\nDarren & Annaley Yates",
        "DISTANCES/TIMES": "¾ length\n1m 13.3s",
        "SP": "100/1"
      },
      {
        "POS": "7th",
        "HORSE/JOCKEY": "Marseille (IRE)\nJames J. Doyle",
        "TRAINER/OWNER": "Julie Camacho\nElite Racing Club",
        "DISTANCES/TIMES": "neck\n1m 13.35s",
        "SP": "22/1"
      },
      {
        "POS": "8th",
        "HORSE/JOCKEY": "Best Bid (IRE)\nJason Hart",
        "TRAINER/OWNER": "John Quinn\nKaniz Bloodstock Investments Ltd",
        "DISTANCES/TIMES": "head\n1m 13.37s",
        "SP": "25/1"
      },
      {
        "POS": "9th",
        "HORSE/JOCKEY": "Chillililli (GB)\nConnor Beasley",
        "TRAINER/OWNER": "Bryan Smart\nMr Shaun Tolley",
        "DISTANCES/TIMES": "2½ lengths\n1m 13.78s",
        "SP": "100/1"
      },
      {
        "POS": "10th",
        "HORSE/JOCKEY": "She's Zoff (IRE)\nCam Hardie",
        "TRAINER/OWNER": "John Quinn\nRacing Ventures",
        "DISTANCES/TIMES": "1½ length\n1m 14.03s",
        "SP": "40/1"
      },
      {
        "POS": "11th",
        "HORSE/JOCKEY": "Remal Dubai (USA)\nJames Doyle",
        "TRAINER/OWNER": "Saeed bin Suroor\nGodolphin",
        "DISTANCES/TIMES": "½ length\n1m 14.1s",
        "SP": "13/8"
      },
      {
        "POS": "12th",
        "HORSE/JOCKEY": "Cool Run Girl (IRE)\nDavid Allan",
        "TRAINER/OWNER": "Iain Jardine\nMr George Brian Davidson",
        "DISTANCES/TIMES": "neck\n1m 14.14s",
        "SP": "20/1"
      },
      {
        "POS": "13th",
        "HORSE/JOCKEY": "Miss Quick (GB)\nP. J. McDonald",
        "TRAINER/OWNER": "Ann Duffield\nMr J. Acheson",
        "DISTANCES/TIMES": "½ length\n1m 14.23s",
        "SP": "33/1"
      },
      {
        "POS": "14th",
        "HORSE/JOCKEY": "Tilly Devine (GB)\nLuke Morris",
        "TRAINER/OWNER": "Scott Dixon\nShowstoppers Racing",
        "DISTANCES/TIMES": "3 lengths\n1m 14.74s",
        "SP": "100/1"
      }
    ]
  },
  {
    "TIME": "8:20PM",
    "NAME": "THE INVESTING FOR THE FUTURE HANDICAP STAKES (CLASS 4) (DIV I)",
    "DISTANCE": "5f",
    "WINNER": "Rich Again (IRE)",
    "URL": "result/#!/2016/12382/22356/0/",
    "details": {
      "Runners:": "12 RUNNERS",
      "Prize Money:": "£7,500.00",
      "Race Distance:": "5f",
      "Race Going:": "Standard",
      "Horse Age:": "3YO+",
      "Rating:": "71-85",
      "Min Weight:": "8st 7lbs"
    },
    "horses": [
      {
        "POS": "1st",
        "HORSE/JOCKEY": "Rich Again (IRE)\nP. J. McDonald\nHandicap Ran Off:76\nBHA Performance Figure: 81",
        "TRAINER/OWNER": "James Bethell\nMr Richard T. Vickers",
        "DISTANCES/TIMES": "0m 58.48s",
        "SP": "17/2"
      },
      {
        "POS": "2nd",
        "HORSE/JOCKEY": "Ziggy Lee (GB)\nAdam McNamara\nHandicap Ran Off:80\nBHA Performance Figure: 83",
        "TRAINER/OWNER": "Lawrence Mullaney\nRothmere Racing Limited",
        "DISTANCES/TIMES": "¾ length\n0m 58.62s",
        "SP": "12/1"
      },
      {
        "POS": "3rd",
        "HORSE/JOCKEY": "Just Us Two (IRE)\nJames Doyle\nHandicap Ran Off:83\nBHA Performance Figure: 83",
        "TRAINER/OWNER": "Robert Cowell\nMr Abdulla Al Mansoori",
        "DISTANCES/TIMES": "½ length\n0m 58.7s",
        "SP": "10/1"
      },
      {
        "POS": "4th",
        "HORSE/JOCKEY": "Desert Ace (IRE)\nClifford Lee\nHandicap Ran Off:82\nBHA Performance Figure: 79",
        "TRAINER/OWNER": "Iain Jardine\nExcelsior Racing Ltd",
        "DISTANCES/TIMES": "1¼ length\n0m 58.93s",
        "SP": "5/1"
      },
      {
        "POS": "5th",
        "HORSE/JOCKEY": "Bondi Beach Boy (GB)\nNathan Evans\nHandicap Ran Off:82\nBHA Performance Figure: 75",
        "TRAINER/OWNER": "James Turner\nMr G. R. Turner & Mr H. Turner",
        "DISTANCES/TIMES": "1 length\n0m 59.08s",
        "SP": "7/1"
      },
      {
        "POS": "6th",
        "HORSE/JOCKEY": "Noble Storm (USA)\nCameron Noble\nHandicap Ran Off:82\nBHA Performance Figure: 75",
        "TRAINER/OWNER": "Ed McMahon\nDr Hugh Jones & Partner",
        "DISTANCES/TIMES": "nose\n0m 59.08s",
        "SP": "12/1"
      },
      {
        "POS": "7th",
        "HORSE/JOCKEY": "Buccaneers Vault (IRE)\nConnor Beasley\nHandicap Ran Off:77\nBHA Performance Figure: 70",
        "TRAINER/OWNER": "Michael Dods\nMr D. Neale",
        "DISTANCES/TIMES": "Short head\n0m 59.09s",
        "SP": "20/1"
      },
      {
        "POS": "8th",
        "HORSE/JOCKEY": "Cocoa Beach (IRE)\nLuke Morris\nHandicap Ran Off:81\nBHA Performance Figure: 67",
        "TRAINER/OWNER": "Sir Mark Prescott Bt\nMr Donald R. Dizney",
        "DISTANCES/TIMES": "2½ lengths\n0m 59.49s",
        "SP": "11/2"
      },
      {
        "POS": "9th",
        "HORSE/JOCKEY": "May Rose (IRE)\nJim Crowley\nHandicap Ran Off:78\nBHA Performance Figure: 62",
        "TRAINER/OWNER": "Charles Hills\nSaleh Al Homaizi & Imad Al Sagar",
        "DISTANCES/TIMES": "½ length\n0m 59.59s",
        "SP": "5/1"
      },
      {
        "POS": "10th",
        "HORSE/JOCKEY": "Crosse Fire (GB)\nDale Swift\nHandicap Ran Off:85\nBHA Performance Figure: 65",
        "TRAINER/OWNER": "Scott Dixon\nPaul J Dixon & Darren Lucas",
        "DISTANCES/TIMES": "1¼ length\n0m 59.79s",
        "SP": "50/1"
      },
      {
        "POS": "11th",
        "HORSE/JOCKEY": "Appleberry (IRE)\nAndrew Mullen\nHandicap Ran Off:76\nBHA Performance Figure: 56",
        "TRAINER/OWNER": "Michael Appleby\nM J Golding, T Pryke, M Appleby",
        "DISTANCES/TIMES": "head\n0m 59.81s",
        "SP": "25/1"
      },
      {
        "POS": "12th",
        "HORSE/JOCKEY": "Sandra's Secret (IRE)\nDavid Allan\nHandicap Ran Off:80\nBHA Performance Figure: 53",
        "TRAINER/OWNER": "Les Eyre\nSunpak Potatoes",
        "DISTANCES/TIMES": "2¼ lengths\n1m 0.19s",
        "SP": "9/1"
      },
      {
        "POS": "NR",
        "HORSE/JOCKEY": "Astrophysics (GB)\nNon Runner\nCurrent handicap mark: T:53",
        "TRAINER/OWNER": "Lynn Siddall\nMr Jimmy Kay",
        "SP": "--"
      },
      {
        "POS": "NR",
        "HORSE/JOCKEY": "Bertie Blu Boy (GB)\nNon Runner",
        "TRAINER/OWNER": "Lisa Williamson\nB & B Hygiene Limited",
        "SP": "--"
      }
    ]
  },
  {
    "TIME": "8:50PM",
    "NAME": "THE INVESTING FOR THE FUTURE HANDICAP STAKES (CLASS 4) (DIV II)",
    "DISTANCE": "5f",
    "WINNER": "Aprovado (IRE)",
    "URL": "result/#!/2016/12382/22356/1/",
    "details": {
      "Runners:": "9 RUNNERS",
      "Prize Money:": "£7,500.00",
      "Race Distance:": "5f",
      "Race Going:": "Standard",
      "Horse Age:": "3YO+",
      "Rating:": "71-85",
      "Min Weight:": "8st 7lbs"
    },
    "horses": [
      {
        "POS": "1st",
        "HORSE/JOCKEY": "Aprovado (IRE)\nConnor Beasley\nHandicap Ran Off:77\nBHA Performance Figure: 80",
        "TRAINER/OWNER": "Michael Dods\nHanson, McKiver, Percival",
        "DISTANCES/TIMES": "0m 58.46s",
        "SP": "10/1"
      },
      {
        "POS": "2nd",
        "HORSE/JOCKEY": "Rosina (GB)\nP. J. McDonald\nHandicap Ran Off:80\nBHA Performance Figure: 81",
        "TRAINER/OWNER": "Ann Duffield\nMs J. Bianco",
        "DISTANCES/TIMES": "½ length\n0m 58.55s",
        "SP": "7/1"
      },
      {
        "POS": "3rd",
        "HORSE/JOCKEY": "Sir Domino (FR)\nGraham Lee\nHandicap Ran Off:74\nBHA Performance Figure: 73",
        "TRAINER/OWNER": "Kevin Ryan\nHambleton Racing Ltd XXXV",
        "DISTANCES/TIMES": "¾ length\n0m 58.68s",
        "SP": "10/1"
      },
      {
        "POS": "4th",
        "HORSE/JOCKEY": "First Bombardment (GB)\nPhillip Makin\nHandicap Ran Off:78\nBHA Performance Figure: 73",
        "TRAINER/OWNER": "David O'Meara\nNorthern Hart Racing & Partner",
        "DISTANCES/TIMES": "1¾ length\n0m 58.97s",
        "SP": "6/1"
      },
      {
        "POS": "5th",
        "HORSE/JOCKEY": "Elusivity (IRE)\nPaul Mulrennan\nHandicap Ran Off:82\nBHA Performance Figure: 72",
        "TRAINER/OWNER": "Conor Dore\nMrs Louise Marsh",
        "DISTANCES/TIMES": "1¼ length\n0m 59.2s",
        "SP": "14/1"
      },
      {
        "POS": "6th",
        "HORSE/JOCKEY": "Cosmic Chatter (GB)\nJames Sullivan\nHandicap Ran Off:81\nBHA Performance Figure: 66",
        "TRAINER/OWNER": "Ruth Carr\nGrange Park Racing VII",
        "DISTANCES/TIMES": "1¾ length\n0m 59.47s",
        "SP": "9/2"
      },
      {
        "POS": "7th",
        "HORSE/JOCKEY": "Oriental Relation (IRE)\nTom Eaves\nHandicap Ran Off:83\nBHA Performance Figure: 67",
        "TRAINER/OWNER": "James Given\nThe Cool Silk Partnership",
        "DISTANCES/TIMES": "neck\n0m 59.51s",
        "SP": "13/2"
      },
      {
        "POS": "8th",
        "HORSE/JOCKEY": "Landing Night (IRE)\nJoey Haynes\nHandicap Ran Off:77\nBHA Performance Figure: 56",
        "TRAINER/OWNER": "Rebecca Menzies\nMr John Dance",
        "DISTANCES/TIMES": "1¾ length\n0m 59.8s",
        "SP": "16/1"
      },
      {
        "POS": "9th",
        "HORSE/JOCKEY": "Baileys Mirage (FR)\nSilvestre De Sousa\nHandicap Ran Off:83\nBHA Performance Figure: 41",
        "TRAINER/OWNER": "Chris Dwyer\nG. R. Bailey Ltd (Baileys Horse Feeds)",
        "DISTANCES/TIMES": "7 lengths\n1m 1.02s",
        "SP": "3/1"
      },
      {
        "POS": "NR",
        "HORSE/JOCKEY": "Outrage (GB)\nNon Runner",
        "TRAINER/OWNER": "Daniel Kubler\nD Blunt & G Middlebrook",
        "SP": "--"
      },
      {
        "POS": "NR",
        "HORSE/JOCKEY": "Gwendolyn (GER)\nNon Runner",
        "TRAINER/OWNER": "Robert Cowell\nSheikh Khalifa, Sheikh Suhaim, QRL",
        "SP": "--"
      },
      {
        "POS": "NR",
        "HORSE/JOCKEY": "Jack Luey (GB)\nNon Runner",
        "TRAINER/OWNER": "Lawrence Mullaney\nThe Jack Partnership & Mr S Rimmer 1",
        "SP": "--"
      },
      {
        "POS": "NR",
        "HORSE/JOCKEY": "Calypso Choir (GB)\nNon Runner",
        "TRAINER/OWNER": "Sylvester Kirk\nMr J. C. Smith",
        "SP": "--"
      },
      {
        "POS": "NR",
        "HORSE/JOCKEY": "Tikthebox (IRE)\nNon Runner",
        "TRAINER/OWNER": "David Brown\nBrown, Bolland, Goforth & Watson",
        "SP": "--"
      }
    ]
  }
]