[
  {
    "TIME": "1:50PM",
    "NAME": "THE BET10GET10 AT VICKERS.BET 'NATIONAL HUNT' MAIDEN HURDLE RACE (CLASS 4) (GBB RACE)",
    "DISTANCE": "2m 5f 200y",
    "WINNER": "Drakes Well (IRE)",
    "URL": "result/#!/2021/816/2744/0/",
    "details": {
      "Runners:": "7 RUNNERS",
      "Prize Money:": "£5,800.00",
      "Race Distance:": "2m 5f 200y",
      "Race Going:": "Good to Firm, Good in places",
      "Horse Age:": "4YO+",
      "Horse Type:": "MAIDEN",
      "Handicapper:": "Michael Harris"
    },
    "horses": [
      {
        "POS": "1st",
        "HORSE/JOCKEY": "Drakes Well (IRE)\nArchie Bellamy\nCurrent handicap mark: S:108",
        "TRAINER/OWNER": "David Bridgwater\nMr Stephen Corbett",
        "DISTANCES/TIMES": "5m 14.4s",
        "SP": "Evens"
      },
      {
        "POS": "2nd",
        "HORSE/JOCKEY": "Master Malcolm (GB)\nBen Jones\nCurrent handicap mark: S:98",
        "TRAINER/OWNER": "Emma-Jane Bishop\nMrs Clare Richmond-Watson",
        "DISTANCES/TIMES": "37 lengths\n5m 21.88s",
        "SP": "10/3"
      },
      {
        "POS": "3rd",
        "HORSE/JOCKEY": "Benny Flies High (IRE)\nNick Scholfield",
        "TRAINER/OWNER": "Sarah Humphrey\nHook Lane Syndicate",
        "DISTANCES/TIMES": "9 lengths\n5m 23.67s",
        "SP": "66/1"
      },
      {
        "POS": "4th",
        "HORSE/JOCKEY": "Iron In The Soul (GB)\nTabitha Worsley",
        "TRAINER/OWNER": "Heather Cobb\nMrs H. J. Cobb",
        "DISTANCES/TIMES": "29 lengths\n5m 29.43s",
        "SP": "28/1"
      },
      {
        "POS": "5th",
        "HORSE/JOCKEY": "Silent Ocean (IRE)\nAlan Doyle",
        "TRAINER/OWNER": "Katharine Davis\nMr D. White",
        "DISTANCES/TIMES": "3¼ lengths\n5m 30.09s",
        "SP": "50/1"
      },
      {
        "POS": "6th",
        "HORSE/JOCKEY": "Filthy Lucca (GB)\nDavid Noonan",
        "TRAINER/OWNER": "Richard Mitchell\nRay & Sue Dodd Partnership",
        "DISTANCES/TIMES": "104 lengths\n5m 50.8s",
        "SP": "66/1"
      },
      {
        "POS": "DNF",
        "HORSE/JOCKEY": "Belle Jour (IRE)\nJoshua Moore",
        "TRAINER/OWNER": "Chris Gordon\nMr L. Gilbert",
        "SP": "15/8"
      }
    ]
  },
  {
    "TIME": "2:25PM",
    "NAME": "THE DOWNLOAD THE VICKERS.BET APP NOVICES' HANDICAP STEEPLE CHASE (CLASS 4) (GBB RACE)",
    "DISTANCE": "2m 5f 171y",
    "WINNER": "Big 'n Better",
    "URL": "result/#!/2021/816/14586/0/",
    "details": {
      "Runners:": "7 RUNNERS",
      "Prize Money:": "£8,000.00",
      "Race Distance:": "2m 5f 171y",
      "Race Going:": "Good to Firm",
      "Horse Age:": "5YO+",
      "Horse Type:": "NOVICE",
      "Rating:": "0-110",
      "Min Weight:": "10st 0lbs",
      "Weights Raised:": "3lbs",
      "Handicapper:": "Martin Greenwood"
    },
    "horses": [
      {
        "POS": "1st",
        "HORSE/JOCKEY": "Big 'n Better (GB)\nMarc Goldstein\nHandicap Ran Off:98\nBHA Performance Figure: 107",
        "TRAINER/OWNER": "Michael Madgwick\nMr W. Smith",
        "DISTANCES/TIMES": "5m 22.95s",
        "SP": "11/1"
      },
      {
        "POS": "2nd",
        "HORSE/JOCKEY": "Arc of Bubbles (IRE)\nPaul O'Brien\nHandicap Ran Off:85\nBHA Performance Figure: 84",
        "TRAINER/OWNER": "Helen Nelmes\nMr M J Hoskins",
        "DISTANCES/TIMES": "11 lengths\n5m 25.06s",
        "SP": "12/1"
      },
      {
        "POS": "3rd",
        "HORSE/JOCKEY": "Old Harry Rocks (IRE)\nA. P. Heskin\nHandicap Ran Off:98\nBHA Performance Figure: 95",
        "TRAINER/OWNER": "Sophie Leech\nMr G. Thompson",
        "DISTANCES/TIMES": "1¾ length\n5m 25.4s",
        "SP": "2/1"
      },
      {
        "POS": "4th",
        "HORSE/JOCKEY": "Deewhy (IRE)\nDanny Burton\nHandicap Ran Off:80\nBHA Performance Figure: 67",
        "TRAINER/OWNER": "Linda Jewell\nMr David Yeadon",
        "DISTANCES/TIMES": "11 lengths\n5m 27.59s",
        "SP": "50/1"
      },
      {
        "POS": "5th",
        "HORSE/JOCKEY": "Sunny Express (IRE)\nJonathan Burke\nHandicap Ran Off:106\nBHA Performance Figure: 93",
        "TRAINER/OWNER": "Warren Greatrex\nMr M. Duthie",
        "DISTANCES/TIMES": "Head\n5m 27.62s",
        "SP": "11/4"
      },
      {
        "POS": "6th",
        "HORSE/JOCKEY": "Silver Nickel (IRE)\nMicheal Nolan\nHandicap Ran Off:101\nBHA Performance Figure: 86",
        "TRAINER/OWNER": "Seamus Mullins\nMrs Deborah Potter",
        "DISTANCES/TIMES": "2¼ lengths\n5m 28.08s",
        "SP": "9/4"
      },
      {
        "POS": "DNF",
        "HORSE/JOCKEY": "Midnight Trouble (GB)\nHarry Bannister\nHandicap Ran Off:93\nBHA Performance Figure: 0",
        "TRAINER/OWNER": "Emma-Jane Bishop\nMrs Jane Organ",
        "SP": "33/1"
      },
      {
        "POS": "WD",
        "HORSE/JOCKEY": "Churchtown Glen (IRE)\nKielan Woods",
        "TRAINER/OWNER": "Michelle Bryant\nMiss M P Bryant, David & Eileen Bryant",
        "SP": "--"
      },
      {
        "POS": "WD",
        "HORSE/JOCKEY": "Black Centaur (IRE)\nJoshua Moore",
        "TRAINER/OWNER": "Chris Gordon\nDavies, King, Selway, Wavish",
        "SP": "--"
      }
    ]
  },
  {
    "TIME": "3:00PM",
    "NAME": "THE VICKERS.BET LIVE CASINO HANDICAP HURDLE RACE (CLASS 5)",
    "DISTANCE": "2m 1f 198y",
    "WINNER": "Mawlood (IRE)",
    "URL": "result/#!/2021/816/2740/0/",
    "details": {
      "Runners:": "15 RUNNERS",
      "Prize Money:": "£5,779.00",
      "Race Distance:": "2m 1f 198y",
      "Race Going:": "Good to Firm",
      "Horse Age:": "4YO+",
      "Rating:": "0-105",
      "Min Weight:": "10st 0lbs",
      "Handicapper:": "Chris Nash"
    },
    "horses": [
      {
        "POS": "1st",
        "HORSE/JOCKEY": "Mawlood (IRE)\nTabitha Worsley\nHandicap Ran Off:81\nBHA Performance Figure: 85\nCurrent handicap mark: S:66 H:66",
        "TRAINER/OWNER": "Phil Middleton\nMr P. W. Middleton",
        "DISTANCES/TIMES": "4m 9.44s",
        "SP": "7/2"
      },
      {
        "POS": "2nd",
        "HORSE/JOCKEY": "Tamaris (IRE)\nJamie Moore\nHandicap Ran Off:102\nBHA Performance Figure: 102\nCurrent handicap mark: S:102",
        "TRAINER/OWNER": "Gary Moore\nTeam Tasker",
        "DISTANCES/TIMES": "2 lengths\n4m 9.83s",
        "SP": "15/2"
      },
      {
        "POS": "3rd",
        "HORSE/JOCKEY": "Serveontime (IRE)\nCharlie Price\nHandicap Ran Off:79\nBHA Performance Figure: 76",
        "TRAINER/OWNER": "Helen Nelmes\nMr K. A. Nelmes",
        "DISTANCES/TIMES": "2¾ lengths\n4m 10.36s",
        "SP": "33/1"
      },
      {
        "POS": "4th",
        "HORSE/JOCKEY": "Test Ride (IRE)\nRobert Dunne\nHandicap Ran Off:80\nBHA Performance Figure: 75",
        "TRAINER/OWNER": "Neil Mulholland\nThe Affordable (3) Partnership",
        "DISTANCES/TIMES": "2½ lengths\n4m 10.84s",
        "SP": "14/1"
      },
      {
        "POS": "5th",
        "HORSE/JOCKEY": "New Zealander (GB)\nKielan Woods\nHandicap Ran Off:99\nBHA Performance Figure: 88",
        "TRAINER/OWNER": "Graeme McPherson\nThe McPherson Racing Partnership",
        "DISTANCES/TIMES": "6½ lengths\n4m 12.12s",
        "SP": "28/1"
      },
      {
        "POS": "6th",
        "HORSE/JOCKEY": "Magical Thomas (GB)\nKevin Brogan\nHandicap Ran Off:92\nBHA Performance Figure: 68",
        "TRAINER/OWNER": "Neil Mulholland\nG. P. and Miss S. J. Hayes",
        "DISTANCES/TIMES": "14 lengths\n4m 14.84s",
        "SP": "10/3"
      },
      {
        "POS": "7th",
        "HORSE/JOCKEY": "Jumping Jack (IRE)\nJay Tidball\nHandicap Ran Off:90\nBHA Performance Figure: 58",
        "TRAINER/OWNER": "Paddy Butler\nHomewoodgate Racing Club",
        "DISTANCES/TIMES": "9 lengths\n4m 16.63s",
        "SP": "125/1"
      },
      {
        "POS": "8th",
        "HORSE/JOCKEY": "Flash de Clerval (FR)\nDaryl Jacob\nHandicap Ran Off:107\nBHA Performance Figure: 73",
        "TRAINER/OWNER": "Harry Whittington\nValueRacingClub.co.uk",
        "DISTANCES/TIMES": "2 lengths\n4m 17.01s",
        "SP": "22/1"
      },
      {
        "POS": "9th",
        "HORSE/JOCKEY": "Uae Soldier (USA)\nMicheal Nolan\nHandicap Ran Off:81\nBHA Performance Figure: 45",
        "TRAINER/OWNER": "Paddy Butler\nMrs E. Lucey-Butler",
        "DISTANCES/TIMES": "2¼ lengths\n4m 17.48s",
        "SP": "80/1"
      },
      {
        "POS": "10th",
        "HORSE/JOCKEY": "Lady Chuffnell (IRE)\nLuca Morgan\nHandicap Ran Off:106\nBHA Performance Figure: 56",
        "TRAINER/OWNER": "Ben Pauling\nThe Megsons",
        "DISTANCES/TIMES": "15 lengths\n4m 20.53s",
        "SP": "11/2"
      },
      {
        "POS": "DNF",
        "HORSE/JOCKEY": "Midnight Jewel (GB)\nJonathan Burke\nHandicap Ran Off:79\nBHA Performance Figure: 0",
        "TRAINER/OWNER": "Charlie Longsdon\nMs G. E. Morgan",
        "SP": "14/1"
      },
      {
        "POS": "DNF",
        "HORSE/JOCKEY": "Takbeer (IRE)\nMr Jason Dixon\nHandicap Ran Off:105\nBHA Performance Figure: 0",
        "TRAINER/OWNER": "Nikki Evans\nMrs M. Gittings-Watts",
        "SP": "100/1"
      },
      {
        "POS": "DNF",
        "HORSE/JOCKEY": "Vlannon (GB)\nMarc Goldstein\nHandicap Ran Off:104\nBHA Performance Figure: 0",
        "TRAINER/OWNER": "Michael Madgwick\nM Gannon, H Vlatas, M Willis, L N Harmes",
        "SP": "66/1"
      },
      {
        "POS": "DNF",
        "HORSE/JOCKEY": "Nachi Falls (GB)\nDavid Noonan\nHandicap Ran Off:94\nBHA Performance Figure: 0",
        "TRAINER/OWNER": "Nigel Hawke\nMr R Weeks and Nigel Hawke Racing Club",
        "SP": "16/1"
      },
      {
        "POS": "DNF",
        "HORSE/JOCKEY": "Espressino (GB)\nBryan Carver\nHandicap Ran Off:98\nBHA Performance Figure: 0",
        "TRAINER/OWNER": "Chris Down\nMrs S. M. Trump",
        "SP": "6/1"
      },
      {
        "POS": "NR",
        "HORSE/JOCKEY": "Second Chapter (IRE)\nNon Runner",
        "TRAINER/OWNER": "Max Young\nMr D. Broadhurst",
        "SP": "--"
      }
    ]
  },
  {
    "TIME": "3:35PM",
    "NAME": "THE VICKERS TELEPHONE BETTING 01325 402001 HANDICAP STEEPLE CHASE (CLASS 5)",
    "DISTANCE": "3m 2f 44y",
    "WINNER": "Max Dynamo",
    "URL": "result/#!/2021/816/2739/0/",
    "details": {
      "Runners:": "11 RUNNERS",
      "Prize Money:": "£6,061.00",
      "Race Distance:": "3m 2f 44y",
      "Race Going:": "Good to Firm",
      "Horse Age:": "5YO+",
      "Rating:": "0-105",
      "Min Weight:": "10st 0lbs",
      "Handicapper:": "Martin Greenwood"
    },
    "horses": [
      {
        "POS": "1st",
        "HORSE/JOCKEY": "Max Dynamo (GB)\nBen Jones\nHandicap Ran Off:84\nBHA Performance Figure: 91\nCurrent handicap mark: S:112",
        "TRAINER/OWNER": "Emma-Jane Bishop\nMrs M. J. Wilson",
        "DISTANCES/TIMES": "6m 27.8s",
        "SP": "9/4"
      },
      {
        "POS": "2nd",
        "HORSE/JOCKEY": "Friends Don't Ask (GB)\nNick Scholfield\nHandicap Ran Off:102\nBHA Performance Figure: 105\nCurrent handicap mark: S:100",
        "TRAINER/OWNER": "Martin Smith\nMr Robert P Clarke and Partners",
        "DISTANCES/TIMES": "3¾ lengths\n6m 28.52s",
        "SP": "9/2"
      },
      {
        "POS": "3rd",
        "HORSE/JOCKEY": "Uallrightharry (IRE)\nJamie Moore\nHandicap Ran Off:107\nBHA Performance Figure: 103\nCurrent handicap mark: S:93",
        "TRAINER/OWNER": "Linda Jewell\nMrs S. Stanier",
        "DISTANCES/TIMES": "8½ lengths\n6m 30.18s",
        "SP": "28/1"
      },
      {
        "POS": "4th",
        "HORSE/JOCKEY": "Unai (IRE)\nDaryl Jacob\nHandicap Ran Off:105\nBHA Performance Figure: 101\nCurrent handicap mark: S:74",
        "TRAINER/OWNER": "Ben Pauling\nMr Simon Munir & Mr Isaac Souede",
        "DISTANCES/TIMES": "Neck\n6m 30.24s",
        "SP": "11/4"
      },
      {
        "POS": "5th",
        "HORSE/JOCKEY": "Legend of Zorro (IRE)\nBryan Carver\nHandicap Ran Off:100\nBHA Performance Figure: 90",
        "TRAINER/OWNER": "Chris Honour\nMr G. Thompson",
        "DISTANCES/TIMES": "7 lengths\n6m 31.6s",
        "SP": "15/2"
      },
      {
        "POS": "6th",
        "HORSE/JOCKEY": "His Dream (IRE)\nPhilip Armson\nHandicap Ran Off:98\nBHA Performance Figure: 85",
        "TRAINER/OWNER": "Jonjo O'Neill\nJonjo O'Neill Racing Club",
        "DISTANCES/TIMES": "3½ lengths\n6m 32.28s",
        "SP": "22/1"
      },
      {
        "POS": "DNF",
        "HORSE/JOCKEY": "Tiger Sam (IRE)\nTabitha Worsley\nHandicap Ran Off:79\nBHA Performance Figure: 0",
        "TRAINER/OWNER": "Laura Hurley\nMiss Laura Hurley",
        "SP": "100/1"
      },
      {
        "POS": "DNF",
        "HORSE/JOCKEY": "Mogestic (IRE)\nMicheal Nolan\nHandicap Ran Off:83\nBHA Performance Figure: 0",
        "TRAINER/OWNER": "Seamus Mullins\nMrs J. C. Scorgie",
        "SP": "14/1"
      },
      {
        "POS": "DNF",
        "HORSE/JOCKEY": "Darsi Rose (IRE)\nDavid Prichard\nHandicap Ran Off:79\nBHA Performance Figure: 0",
        "TRAINER/OWNER": "Laura Hurley\nMrs R. Hurley",
        "SP": "125/1"
      },
      {
        "POS": "DNF",
        "HORSE/JOCKEY": "Plantagenet (GB)\nDaniel Sansom\nHandicap Ran Off:105\nBHA Performance Figure: 0",
        "TRAINER/OWNER": "Seamus Mullins\nMrs P. de W. Johnson",
        "SP": "9/1"
      },
      {
        "POS": "DNF",
        "HORSE/JOCKEY": "It's For Alan (GB)\nPage Fuller\nHandicap Ran Off:92\nBHA Performance Figure: 0",
        "TRAINER/OWNER": "Jo Davis\nTony Worth & Vic Bedley",
        "SP": "14/1"
      },
      {
        "POS": "NR",
        "HORSE/JOCKEY": "Shanroe Smooch (IRE)\nNon Runner",
        "TRAINER/OWNER": "Richenda Ford\nMr & Mrs K. B. Snook",
        "SP": "--"
      },
      {
        "POS": "NR",
        "HORSE/JOCKEY": "Arthur's Reuben (GB)\nNon Runner",
        "TRAINER/OWNER": "Sean Curran\nMr A. White",
        "SP": "--"
      }
    ]
  },
  {
    "TIME": "4:10PM",
    "NAME": "THE TRY OUR BET-BUILDER AT VICKERS.BET HANDICAP HURDLE RACE (CLASS 4)",
    "DISTANCE": "3m 2f",
    "WINNER": "Sammylou (IRE)",
    "URL": "result/#!/2021/816/2742/0/",
    "details": {
      "Runners:": "4 RUNNERS",
      "Prize Money:": "£7,200.00",
      "Race Distance:": "3m 2f",
      "Race Going:": "Good to Firm",
      "Horse Age:": "4YO+",
      "Rating:": "0-120",
      "Min Weight:": "10st 0lbs",
      "Weights Raised:": "1lbs",
      "Handicapper:": "Michael Harris"
    },
    "horses": [
      {
        "POS": "1st",
        "HORSE/JOCKEY": "Sammylou (IRE)\nKielan Woods\nHandicap Ran Off:119\nBHA Performance Figure: 119\nCurrent handicap mark: H:96",
        "TRAINER/OWNER": "Graeme McPherson\nDL Adams, JA Adams & G McPherson",
        "DISTANCES/TIMES": "6m 24.15s",
        "SP": "9/4"
      },
      {
        "POS": "2nd",
        "HORSE/JOCKEY": "Lithic (IRE)\nKevin Brogan\nHandicap Ran Off:118\nBHA Performance Figure: 116",
        "TRAINER/OWNER": "Jonjo O'Neill\nThe Stone Composers",
        "DISTANCES/TIMES": "*1¼ length\n6m 24.45s",
        "SP": "10/3"
      },
      {
        "POS": "3rd",
        "HORSE/JOCKEY": "Milrow (IRE)\nA. P. Heskin\nHandicap Ran Off:104\nBHA Performance Figure: 98",
        "TRAINER/OWNER": "Sophie Leech\nMr John Cocks",
        "DISTANCES/TIMES": "4¾ lengths\n6m 25.4s",
        "SP": "7/4"
      },
      {
        "POS": "4th",
        "HORSE/JOCKEY": "Rumble B (IRE)\nNick Scholfield\nHandicap Ran Off:110\nBHA Performance Figure: 102\nCurrent handicap mark: H:87",
        "TRAINER/OWNER": "Sarah Humphrey\nThe Pheasant Plotters",
        "DISTANCES/TIMES": "2½ lengths\n6m 25.89s",
        "SP": "11/2"
      },
      {
        "POS": "NR",
        "HORSE/JOCKEY": "The Tin Miner (IRE)\nNon Runner",
        "TRAINER/OWNER": "Chris Gordon\nMrs B. Ansell",
        "SP": "--"
      },
      {
        "POS": "NR",
        "HORSE/JOCKEY": "Top Man (IRE)\nNon Runner",
        "TRAINER/OWNER": "Chris Gordon\nBroadsword Group Ltd",
        "SP": "--"
      }
    ]
  },
  {
    "TIME": "4:45PM",
    "NAME": "THE VICKERS.BET BOG 7 DAYS A WEEK HANDICAP STEEPLE CHASE (CLASS 3)",
    "DISTANCE": "2m 1f 201y",
    "WINNER": "Carolines Charm (IRE)",
    "URL": "result/#!/2021/816/20422/0/",
    "details": {
      "Runners:": "3 RUNNERS",
      "Prize Money:": "£12,200.00",
      "Race Distance:": "2m 1f 201y",
      "Race Going:": "Good to Firm",
      "Horse Age:": "5YO+",
      "Rating:": "0-130",
      "Min Weight:": "10st 0lbs",
      "Handicapper:": "Martin Greenwood"
    },
    "horses": [
      {
        "POS": "1st",
        "HORSE/JOCKEY": "Carolines Charm (IRE)\nRobert Dunne\nHandicap Ran Off:129\nBHA Performance Figure: 130",
        "TRAINER/OWNER": "Neil Mulholland\nThe Affordable Partnership",
        "DISTANCES/TIMES": "4m 30.5s",
        "SP": "Evens"
      },
      {
        "POS": "2nd",
        "HORSE/JOCKEY": "Baby King (IRE)\nJonathan Burke\nHandicap Ran Off:117\nBHA Performance Figure: 117",
        "TRAINER/OWNER": "Tom George\nAbout Two Weeks",
        "DISTANCES/TIMES": "Neck\n4m 30.55s",
        "SP": "4/1"
      },
      {
        "POS": "3rd",
        "HORSE/JOCKEY": "Master Burbidge (GB)\nA. P. Heskin\nHandicap Ran Off:110\nBHA Performance Figure: 108",
        "TRAINER/OWNER": "Neil Mulholland\nDajam Ltd",
        "DISTANCES/TIMES": "2¾ lengths\n4m 31.13s",
        "SP": "13/8"
      },
      {
        "POS": "NR",
        "HORSE/JOCKEY": "Iconic Muddle (GB)\nNon Runner",
        "TRAINER/OWNER": "Gary Moore\nSaloop",
        "SP": "--"
      }
    ]
  },
  {
    "TIME": "5:20PM",
    "NAME": "THE VICKERS.BET FREE BETS WITH BET CLUB HANDICAP HURDLE RACE (CLASS 5) (DIV I)",
    "DISTANCE": "2m 5f 200y",
    "WINNER": "Kilchreest Moon (IRE)",
    "URL": "result/#!/2021/816/2741/0/",
    "details": {
      "Runners:": "8 RUNNERS",
      "Prize Money:": "£5,779.00",
      "Race Distance:": "2m 5f 200y",
      "Race Going:": "Good to Firm",
      "Horse Age:": "4YO+",
      "Rating:": "0-100",
      "Min Weight:": "10st 0lbs",
      "Weights Raised:": "3lbs",
      "Handicapper:": "Michael Harris"
    },
    "horses": [
      {
        "POS": "1st",
        "HORSE/JOCKEY": "Kilchreest Moon (IRE)\nNick Scholfield\nHandicap Ran Off:80\nBHA Performance Figure: 84",
        "TRAINER/OWNER": "Henry Oliver\nSue Howell",
        "DISTANCES/TIMES": "5m 15.7s",
        "SP": "9/4"
      },
      {
        "POS": "2nd",
        "HORSE/JOCKEY": "Lapford Lad (GB)\nMicheal Nolan\nHandicap Ran Off:74\nBHA Performance Figure: 75",
        "TRAINER/OWNER": "Susan Gardner\nMr A. Leach",
        "DISTANCES/TIMES": "½ length\n5m 15.8s",
        "SP": "11/1"
      },
      {
        "POS": "3rd",
        "HORSE/JOCKEY": "Jessica Rabbit (GB)\nKielan Woods\nHandicap Ran Off:87\nBHA Performance Figure: 87",
        "TRAINER/OWNER": "Graeme McPherson\nThe Ladies Of Martins Hill",
        "DISTANCES/TIMES": "1 length\n5m 16.01s",
        "SP": "10/3"
      },
      {
        "POS": "4th",
        "HORSE/JOCKEY": "Bazarov (IRE)\nJamie Moore\nHandicap Ran Off:101\nBHA Performance Figure: 98",
        "TRAINER/OWNER": "Archie Watson\nMarco Polo",
        "DISTANCES/TIMES": "3½ lengths\n5m 16.73s",
        "SP": "5/1"
      },
      {
        "POS": "5th",
        "HORSE/JOCKEY": "Noble Glance (GB)\nCharlie Price\nHandicap Ran Off:96\nBHA Performance Figure: 87",
        "TRAINER/OWNER": "Camilla Poulton\nMr D. Newland",
        "DISTANCES/TIMES": "6½ lengths\n5m 17.99s",
        "SP": "9/1"
      },
      {
        "POS": "6th",
        "HORSE/JOCKEY": "King Cool (GB)\nNiall Houlihan\nHandicap Ran Off:93\nBHA Performance Figure: 83",
        "TRAINER/OWNER": "Gary Moore\nMr P. Mott",
        "DISTANCES/TIMES": "½ length\n5m 18.1s",
        "SP": "13/2"
      },
      {
        "POS": "7th",
        "HORSE/JOCKEY": "Full Spes (FR)\nHarry Bannister\nHandicap Ran Off:89\nBHA Performance Figure: 78",
        "TRAINER/OWNER": "Warren Greatrex\nJ & R Eynon, Majithia & AWR Consultancy",
        "DISTANCES/TIMES": "1 length\n5m 18.28s",
        "SP": "22/1"
      },
      {
        "POS": "DNF",
        "HORSE/JOCKEY": "Tango du Roy (IRE)\nDavid Prichard\nHandicap Ran Off:87\nBHA Performance Figure: 0",
        "TRAINER/OWNER": "Nigel Hawke\nMr Ian Prichard",
        "SP": "12/1"
      },
      {
        "POS": "WD",
        "HORSE/JOCKEY": "Furia d'Oudairies (FR)\nNiall Houlihan",
        "TRAINER/OWNER": "Nick Gifford\nMr John Terry",
        "SP": "--"
      },
      {
        "POS": "NR",
        "HORSE/JOCKEY": "Time Is Time (IRE)\nNon Runner",
        "TRAINER/OWNER": "Sarah Robinson\nMr Allan Woodley-Milburn",
        "SP": "--"
      },
      {
        "POS": "NR",
        "HORSE/JOCKEY": "Kalaya (IRE)\nNon Runner",
        "TRAINER/OWNER": "Barry Brennan\nMr David Gibbons",
        "SP": "--"
      }
    ]
  },
  {
    "TIME": "5:50PM",
    "NAME": "THE VICKERS.BET FREE BETS WITH BET CLUB HANDICAP HURDLE RACE (CLASS 5) (DIV II)",
    "DISTANCE": "2m 5f 200y",
    "WINNER": "I'm On Snap (IRE)",
    "URL": "result/#!/2021/816/2741/1/",
    "details": {
      "Runners:": "4 RUNNERS",
      "Prize Money:": "£5,779.00",
      "Race Distance:": "2m 5f 200y",
      "Race Going:": "Good to Firm",
      "Horse Age:": "4YO+",
      "Rating:": "0-100",
      "Min Weight:": "10st 0lbs",
      "Handicapper:": "Michael Harris"
    },
    "horses": [
      {
        "POS": "1st",
        "HORSE/JOCKEY": "I'm On Snap (IRE)\nJonathan Burke\nHandicap Ran Off:87\nBHA Performance Figure: 90",
        "TRAINER/OWNER": "Tom Lacey\nValueRacingClub.co.uk",
        "DISTANCES/TIMES": "5m 21.95s",
        "SP": "8/11"
      },
      {
        "POS": "2nd",
        "HORSE/JOCKEY": "Leading Knight (IRE)\nLuca Morgan\nHandicap Ran Off:90\nBHA Performance Figure: 90",
        "TRAINER/OWNER": "Ben Pauling\nThe Ben Pauling Racing Club",
        "DISTANCES/TIMES": "½ length\n5m 22.05s",
        "SP": "6/4"
      },
      {
        "POS": "3rd",
        "HORSE/JOCKEY": "Steel The China (IRE)\nDanny Burton\nHandicap Ran Off:73\nBHA Performance Figure: 53",
        "TRAINER/OWNER": "Linda Jewell\nCS Partnership",
        "DISTANCES/TIMES": "23 lengths\n5m 26.74s",
        "SP": "18/1"
      },
      {
        "POS": "4th",
        "HORSE/JOCKEY": "Singer In The Sand (IRE)\nNiall Houlihan\nHandicap Ran Off:80\nBHA Performance Figure: 60",
        "TRAINER/OWNER": "Pat Phelan\nMr I. W. Harfitt",
        "DISTANCES/TIMES": "Nose\n5m 26.75s",
        "SP": "16/1"
      },
      {
        "POS": "NR",
        "HORSE/JOCKEY": "Flintara (GB)\nHarry Bannister\nCurrent handicap mark: S:108",
        "TRAINER/OWNER": "Richard Bandey\nLeith Hill Chasers",
        "SP": "--"
      },
      {
        "POS": "NR",
        "HORSE/JOCKEY": "Lemon Shoulder (IRE)\nNon Runner",
        "TRAINER/OWNER": "Cynthia Woods\nMr G. Woods",
        "SP": "--"
      },
      {
        "POS": "NR",
        "HORSE/JOCKEY": "Lake Shore Drive (IRE)\nNon Runner",
        "TRAINER/OWNER": "Johnny Farrelly\nMr Greenfingers Syndicate",
        "SP": "--"
      },
      {
        "POS": "NR",
        "HORSE/JOCKEY": "Espinator (FR)\nNon Runner\nCurrent handicap mark: H:97",
        "TRAINER/OWNER": "Adrian Wintle\nMr S. R. Whistance",
        "SP": "--"
      },
      {
        "POS": "NR",
        "HORSE/JOCKEY": "Watchman (IRE)\nNon Runner",
        "TRAINER/OWNER": "Nikki Evans\nTip of The Sword Racing",
        "SP": "--"
      },
      {
        "POS": "NR",
        "HORSE/JOCKEY": "Soarlikeaneagle (IRE)\nNon Runner",
        "TRAINER/OWNER": "Richard Rowe\nRichard Rowe Racing Partnership",
        "SP": "--"
      },
      {
        "POS": "NR",
        "HORSE/JOCKEY": "Ballymilan (GB)\nNon Runner",
        "TRAINER/OWNER": "Neil Mulholland\nHeart Racing HR2",
        "SP": "--"
      }
    ]
  }
]