[
  {
    "TIME": "4:40PM",
    "NAME": "THE 32Red CASINO MAIDEN FILLIES' STAKES (CLASS 5)",
    "DISTANCE": "5f 216y",
    "WINNER": "Interception (IRE)",
    "URL": "result/#!/2013/14876/27653/0/"
  },
  {
    "TIME": "5:10PM",
    "NAME": "THE BEST ODDS AT bookmakers.co.uk HANDICAP STAKES (CLASS 4)",
    "DISTANCE": "5f 216y",
    "WINNER": "You're The Boss (GB)",
    "URL": "result/#!/2013/14876/27655/0/"
  },
  {
    "TIME": "5:40PM",
    "NAME": "THE 32Red.com MAIDEN AUCTION STAKES (CLASS 5)",
    "DISTANCE": "7f 32y",
    "WINNER": "Art Obsession (IRE)",
    "URL": "result/#!/2013/14876/27654/0/"
  },
  {
    "TIME": "6:10PM",
    "NAME": "THE LADBROKES HANDICAP STAKES (CLASS 4)",
    "DISTANCE": "7f 32y",
    "WINNER": "Ruwaiyan (USA)",
    "URL": "result/#!/2013/14876/27649/0/"
  },
  {
    "TIME": "6:40PM",
    "NAME": "THE 32Red NURSERY HANDICAP STAKES (CLASS 6)",
    "DISTANCE": "1m 141y",
    "WINNER": "Jazzy Lady (IRE)",
    "URL": "result/#!/2013/14876/27651/0/"
  },
  {
    "TIME": "7:10PM",
    "NAME": "THE CORAL APP DOWNLOAD FROM THE APP STORE HANDICAP STAKES (CLASS 5)",
    "DISTANCE": "1m 1f 103y",
    "WINNER": "Landau (IRE)",
    "URL": "result/#!/2013/14876/27652/0/"
  }
]