[
  {
    "TIME": "4:50PM",
    "NAME": "THE LADBROKES HOME OF THE ODDS BOOST NURSERY HANDICAP STAKES (CLASS 4)",
    "DISTANCE": "7f 36y",
    "WINNER": "Blausee (IRE)",
    "URL": "result/#!/2019/13988/48046/0/"
  },
  {
    "TIME": "5:20PM",
    "NAME": "THE BOMBARDIER BRITISH HOPPED AMBER BEER HANDICAP STAKES (CLASS 6)",
    "DISTANCE": "7f 36y",
    "WINNER": "Shamarouski (IRE)",
    "URL": "result/#!/2019/13988/48005/0/"
  },
  {
    "TIME": "5:50PM",
    "NAME": "THE BOMBARDIER GOLDEN BEER HANDICAP STAKES (CLASS 6)",
    "DISTANCE": "1m 142y",
    "WINNER": "Star of Valour (IRE)",
    "URL": "result/#!/2019/13988/48006/0/"
  },
  {
    "TIME": "6:20PM",
    "NAME": "THE BETWAY SELLING STAKES (CLASS 5)",
    "DISTANCE": "5f 21y",
    "WINNER": "Tan",
    "URL": "result/#!/2019/13988/48045/0/"
  },
  {
    "TIME": "6:50PM",
    "NAME": "THE BETWAY HANDICAP STAKES (CLASS 6)",
    "DISTANCE": "1m 1f 104y",
    "WINNER": "First Dance (IRE)",
    "URL": "result/#!/2019/13988/48007/0/"
  },
  {
    "TIME": "7:20PM",
    "NAME": "THE BETWAY CASINO HANDICAP STAKES (CLASS 6)",
    "DISTANCE": "1m 4f 51y",
    "WINNER": "Mrs Ivy",
    "URL": "result/#!/2019/13988/48008/0/"
  },
  {
    "TIME": "7:50PM",
    "NAME": "THE BETWAY HEED YOUR HUNCH NOVICE STAKES (CLASS 5)",
    "DISTANCE": "1m 4f 51y",
    "WINNER": "Bye Bye Lady (FR)",
    "URL": "result/#!/2019/13988/48009/0/"
  },
  {
    "TIME": "8:20PM",
    "NAME": "THE BETWAY NOVICE STAKES (CLASS 5)",
    "DISTANCE": "5f 21y",
    "WINNER": "Great Suspense",
    "URL": "result/#!/2019/13988/48010/0/"
  }
]