[
  {
    "TIME": "2:00PM",
    "NAME": "THE SIS NOVICES' HURDLE RACE (CLASS 4)",
    "DISTANCE": "2m 48y",
    "WINNER": "Kid Valentine (IRE)",
    "URL": "result/#!/2016/927/3366/0/"
  },
  {
    "TIME": "2:30PM",
    "NAME": "THE HEXHAM BOOKMAKERS HANDICAP STEEPLE CHASE (CLASS 5)",
    "DISTANCE": "2m 4f 15y",
    "WINNER": "Whats Up Woody (IRE)",
    "URL": "result/#!/2016/927/23508/0/"
  },
  {
    "TIME": "3:05PM",
    "NAME": "THE LWC NOVICES' HURDLE RACE (CLASS 4)",
    "DISTANCE": "2m 7f 63y",
    "WINNER": "Gully's Edge",
    "URL": "result/#!/2016/927/3369/0/"
  },
  {
    "TIME": "3:40PM",
    "NAME": "FOLLOW HEXHAM ON FACEBOOK HANDICAP HURDLE RACE (CLASS 4)",
    "DISTANCE": "2m 4f 28y",
    "WINNER": "See Double You (IRE)",
    "URL": "result/#!/2016/927/3364/0/"
  },
  {
    "TIME": "4:15PM",
    "NAME": "THE PRIMARY WEBSITES HANDICAP STEEPLE CHASE (CLASS 5)",
    "DISTANCE": "3m 41y",
    "WINNER": "Gibbstown (IRE)",
    "URL": "result/#!/2016/927/3363/0/"
  },
  {
    "TIME": "4:50PM",
    "NAME": "FOLLOW HEXHAM ON TWITTER MAIDEN OPEN NATIONAL HUNT FLAT RACE (CLASS 6)",
    "DISTANCE": "2m 48y",
    "WINNER": "Imperial Eloquence (IRE)",
    "URL": "result/#!/2016/927/3362/0/"
  }
]