[
  {
    "TIME": "2:20PM",
    "NAME": "THE DOWNLOAD THE LADBROKES APP MAIDEN FILLIES' STAKES (CLASS 5)",
    "DISTANCE": "1m 67y",
    "WINNER": "Rosslare (IRE)",
    "URL": "result/#!/2015/805/15117/0/"
  },
  {
    "TIME": "2:50PM",
    "NAME": "THE LADBROKES HANDICAP STAKES (CLASS 5)",
    "DISTANCE": "5f 10y",
    "WINNER": "Kassbaan",
    "URL": "result/#!/2015/805/15120/0/"
  },
  {
    "TIME": "3:25PM",
    "NAME": "THE ROA/RACING POST OWNERS JACKPOT EBF FILLIES' CONDITIONS STAKES (CLASS 2) (PLUS10 RACE)",
    "DISTANCE": "5f 10y",
    "WINNER": "Whatdoiwantthatfor (IRE)",
    "URL": "result/#!/2015/805/4255/0/"
  },
  {
    "TIME": "4:00PM",
    "NAME": "THE BET NOW WITH THE LADBROKES APP HANDICAP STAKES (CLASS 3) (BOBIS RACE)",
    "DISTANCE": "1m 2f 7y",
    "WINNER": "Argus (IRE)",
    "URL": "result/#!/2015/805/15116/0/"
  },
  {
    "TIME": "4:35PM",
    "NAME": "THE DOWNLOAD THE LADBROKES APP HANDICAP STAKES (CLASS 3)",
    "DISTANCE": "1m 67y",
    "WINNER": "Secret Art (IRE)",
    "URL": "result/#!/2015/805/15118/0/"
  },
  {
    "TIME": "5:05PM",
    "NAME": "DOWNLOAD AND BET WITH THE LADBROKES APP HANDICAP STAKES (CLASS 5)",
    "DISTANCE": "1m 67y",
    "WINNER": "Hard To Handel",
    "URL": "result/#!/2015/805/15119/0/"
  },
  {
    "TIME": "5:35PM",
    "NAME": "THIS IS THE LADBROKES LIFE HANDICAP STAKES (CLASS 5)",
    "DISTANCE": "1m 3f 135y",
    "WINNER": "Well Painted (IRE)",
    "URL": "result/#!/2015/805/24863/0/"
  }
]